pacotepypi/modulo.py
pacotepypi145-0.0.1.dist-info/LICENSE
pacotepypi145-0.0.1.dist-info/METADATA
pacotepypi145-0.0.1.dist-info/WHEEL
pacotepypi145-0.0.1.dist-info/top_level.txt
pacotepypi145-0.0.1.dist-info/RECORD
