Metadata-Version: 2.1
Name: pacotepypi145
Version: 0.0.1
Summary: Pacote python para exibir número de 0 a 9
Home-page: https://github.com/murilofarias/pacotepypi
Author: Murilo Dias Ferreira Farias
Author-email: murilo145farias@gmail.com
License: MIT License
Keywords: Pacote
Platform: UNKNOWN
Requires-Dist: numpy
